materialyoucolor-2.0.9.dist-info/RECORD
materialyoucolor-2.0.9.dist-info/METADATA
materialyoucolor-2.0.9.dist-info/WHEEL
materialyoucolor-2.0.9.dist-info/top_level.txt
materialyoucolor-2.0.9.dist-info/LICENSE
materialyoucolor/__init__.py
materialyoucolor/dislike/__init__.py
materialyoucolor/dislike/dislike_analyzer.py
materialyoucolor/quantize/__init__.py
materialyoucolor/quantize/celebi.cpython-39-x86_64-linux-gnu.so
materialyoucolor/temperature/__init__.py
materialyoucolor/temperature/temperature_cache.py
materialyoucolor/hct/hct_solver.py
materialyoucolor/hct/__init__.py
materialyoucolor/hct/viewing_conditions.py
materialyoucolor/hct/hct.py
materialyoucolor/hct/cam16.py
materialyoucolor/palettes/__init__.py
materialyoucolor/palettes/tonal_palette.py
materialyoucolor/palettes/core_palette.py
materialyoucolor/dynamiccolor/__init__.py
materialyoucolor/dynamiccolor/dynamic_color.py
materialyoucolor/dynamiccolor/tone_delta_pair.py
materialyoucolor/dynamiccolor/contrast_curve.py
materialyoucolor/dynamiccolor/material_dynamic_colors.py
materialyoucolor/contrast/__init__.py
materialyoucolor/contrast/contrast.py
materialyoucolor/scheme/scheme_neutral.py
materialyoucolor/scheme/scheme_content.py
materialyoucolor/scheme/__init__.py
materialyoucolor/scheme/scheme_vibrant.py
materialyoucolor/scheme/scheme_fidelity.py
materialyoucolor/scheme/scheme_tonal_spot.py
materialyoucolor/scheme/scheme_android.py
materialyoucolor/scheme/scheme.py
materialyoucolor/scheme/scheme_rainbow.py
materialyoucolor/scheme/scheme_monochrome.py
materialyoucolor/scheme/variant.py
materialyoucolor/scheme/dynamic_scheme.py
materialyoucolor/scheme/scheme_expressive.py
materialyoucolor/scheme/scheme_fruit_salad.py
materialyoucolor/utils/platform_utils.py
materialyoucolor/utils/__init__.py
materialyoucolor/utils/math_utils.py
materialyoucolor/utils/theme_utils.py
materialyoucolor/utils/color_utils.py
materialyoucolor/blend/__init__.py
materialyoucolor/blend/blend.py
materialyoucolor/score/__init__.py
materialyoucolor/score/score.py
