Metadata-Version: 2.1
Name: materialyoucolor
Version: 2.0.9
Summary: Material You color generation algorithms in pure python!
Author: Ansh Dadwal
Author-email: anshdadwal298@gmail.com
License-File: LICENSE
